tpimporter/Excel_Importer.py
tpimporter/TP_Importer.py
tpimporter/TP_Importer_Channels.py
tpimporter/TVTP_Importer.py
tpimporter/TVTP_Importer_Channels.py
tpimporter/__init__.py
tpimporter/adapters/Adapter_for_MAM.py
tpimporter/adapters/Adapter_for_VOD_Reporting_PyQt.py
tpimporter/adapters/Adapter_for_newMAM.py
tpimporter/adapters/Basic_Adapter.py
tpimporter/adapters/__init__.py
tpimporter-0.7.5.dist-info/LICENSE.txt
tpimporter-0.7.5.dist-info/METADATA
tpimporter-0.7.5.dist-info/WHEEL
tpimporter-0.7.5.dist-info/top_level.txt
tpimporter-0.7.5.dist-info/RECORD
