Metadata-Version: 2.1
Name: tpimporter
Version: 0.7.5
Summary: a package to import excel files - specifically our Titelplanung and TV Titelplanung
Home-page: https://github.com/skalizzo/TP_Importer
Author: Christian Richter
Author-email: christian.richter@leoninestudios.com
License: UNKNOWN
Project-URL: Source, https://github.com/skalizzo/TP_Importer
Keywords: Excel importer,Titelplanung,VOD,LEONINE
Platform: UNKNOWN
Classifier: Development Status :: 3 - Alpha
Classifier: Intended Audience :: Developers
Classifier: Topic :: Utilities
Classifier: License :: OSI Approved :: MIT License
Classifier: Programming Language :: Python :: 3
Classifier: Programming Language :: Python :: 3.7
Classifier: Programming Language :: Python :: 3.8
Classifier: Programming Language :: Python :: 3.9
Classifier: Programming Language :: Python :: 3.10
Classifier: Programming Language :: Python :: 3 :: Only
Requires-Python: >=3.7
Requires-Dist: openpyxl
Requires-Dist: msoffcrypto-tool
